peeling/__init__.py
peeling/cellular_compartments.py
peeling/clipantherprocessor.py
peeling/cliprocessor.py
peeling/cliuniprotcommunicator.py
peeling/cliuserinputreader.py
peeling/main.py
peeling/pantherprocessor.py
peeling/processor.py
peeling/uniprotcommunicator.py
peeling/userinputreader.py
peeling/webpantherprocessor.py
peeling/webprocessor.py
peeling/webuniprotcommunicator.py
peeling/webuserinputreader.py
peeling-0.2.4.dist-info/LICENSE
peeling-0.2.4.dist-info/METADATA
peeling-0.2.4.dist-info/WHEEL
peeling-0.2.4.dist-info/entry_points.txt
peeling-0.2.4.dist-info/top_level.txt
peeling-0.2.4.dist-info/RECORD
