Metadata-Version: 2.1
Name: peeling
Version: 0.2.4
Author-email: HHMI Janelia <peeling@janelia.hhmi.org>
License: BSD 3-Clause License
Project-URL: Homepage, https://github.com/JaneliaSciComp/peeling
Classifier: Programming Language :: Python :: 3
Classifier: License :: OSI Approved :: BSD License
Classifier: Operating System :: OS Independent
Requires-Python: >=3.9
License-File: LICENSE
Requires-Dist: anyio ==3.6.2
Requires-Dist: certifi ==2022.9.24
Requires-Dist: charset-normalizer ==2.1.1
Requires-Dist: contourpy ==1.0.6
Requires-Dist: cycler ==0.11.0
Requires-Dist: fonttools ==4.38.0
Requires-Dist: h11 ==0.14.0
Requires-Dist: h2 ==4.1.0
Requires-Dist: hpack ==4.0.0
Requires-Dist: httpcore ==0.16.3
Requires-Dist: httpx ==0.23.1
Requires-Dist: hyperframe ==6.0.1
Requires-Dist: idna ==3.4
Requires-Dist: joblib ==1.2.0
Requires-Dist: kiwisolver ==1.4.4
Requires-Dist: matplotlib ==3.6.3
Requires-Dist: numpy ==1.23.4
Requires-Dist: packaging ==21.3
Requires-Dist: pandas ==1.5.1
Requires-Dist: Pillow ==9.3.0
Requires-Dist: pyparsing ==3.0.9
Requires-Dist: python-dateutil ==2.8.2
Requires-Dist: pytz ==2022.6
Requires-Dist: requests ==2.28.1
Requires-Dist: rfc3986 ==1.5.0
Requires-Dist: scikit-learn ==1.1.3
Requires-Dist: scipy ==1.9.3
Requires-Dist: seaborn ==0.12.2
Requires-Dist: six ==1.16.0
Requires-Dist: sklearn ==0.0
Requires-Dist: sniffio ==1.3.0
Requires-Dist: threadpoolctl ==3.1.0
Requires-Dist: urllib3 ==1.26.12
